postnote/__init__.py
postnote/base.py
postnote/client.py
postnote/display.py
postnote/settings.py
postnote-0.5.1.dist-info/licenses/LICENSE
postnote-0.5.1.dist-info/METADATA
postnote-0.5.1.dist-info/WHEEL
postnote-0.5.1.dist-info/top_level.txt
postnote-0.5.1.dist-info/RECORD
