Metadata-Version: 2.4
Name: postnote
Version: 0.5.1
Summary: A lightweight Postman-like client for Jupyter notebooks and Python projects.
Author-email: Davi Guides <davi.guides@gmail.com>
License-Expression: MIT
Project-URL: Homepage, https://github.com/daviguides/postnote
Project-URL: Repository, https://github.com/daviguides/postnote
Project-URL: Issues, https://github.com/daviguides/postnote/issues
Classifier: Programming Language :: Python :: 3
Classifier: Programming Language :: Python :: 3.11
Classifier: Programming Language :: Python :: 3.12
Classifier: Operating System :: OS Independent
Classifier: Intended Audience :: Developers
Classifier: Topic :: Internet :: WWW/HTTP
Classifier: Topic :: Software Development :: Libraries
Classifier: Topic :: Utilities
Requires-Python: >=3.11
License-File: LICENSE
Requires-Dist: requests>=2.32.0
Requires-Dist: polars>=1.0.0
Requires-Dist: ipython>=8.0.0
Requires-Dist: ipykernel>=6.29.5
Requires-Dist: ipython>=8.36.0
Dynamic: license-file
